zettalens_sdk/__init__.py
zettalens_sdk/zettalnes.py
zettalens_sdk/modules/__init__.py
zettalens_sdk/modules/agent.py
zettalens_sdk/modules/base.py
zettalens_sdk/modules/chat.py
zettalens_sdk/modules/chunk.py
zettalens_sdk/modules/dataset.py
zettalens_sdk/modules/document.py
zettalens_sdk/modules/session.py
zettalens_sdk-1.0.0.dist-info/METADATA
zettalens_sdk-1.0.0.dist-info/WHEEL
zettalens_sdk-1.0.0.dist-info/top_level.txt
zettalens_sdk-1.0.0.dist-info/RECORD
